HolograPy/__init__.py
HolograPy/utils.py
holograpy-0.1.0.dist-info/licenses/LICENSE.txt
holograpy-0.1.0.dist-info/METADATA
holograpy-0.1.0.dist-info/WHEEL
holograpy-0.1.0.dist-info/top_level.txt
holograpy-0.1.0.dist-info/RECORD
