Metadata-Version: 2.4
Name: HolograPy
Version: 0.1.0
Summary: Tools for 3D holography, acoustic field simulation, and grid generation
Home-page: https://github.com/JamesAHardwick/HolograPy
Author: James Hardwick
License: MIT
Classifier: Programming Language :: Python :: 3
Classifier: License :: OSI Approved :: MIT License
Classifier: Operating System :: OS Independent
Classifier: Topic :: Scientific/Engineering :: Physics
Requires-Python: >=3.8
License-File: LICENSE.txt
Requires-Dist: numpy
Requires-Dist: Pillow
Requires-Dist: plotly
Dynamic: license-file
